ptvertmenu/__init__.py
ptvertmenu/dynvertmenu.py
ptvertmenu/py.typed
ptvertmenu/vertmenu.py
ptvertmenu/vertmenuuicontrol.py
ptvertmenu-0.2.2.data/data/share/doc/python-ptvertmenu/AUTHORS
ptvertmenu-0.2.2.data/data/share/doc/python-ptvertmenu/LICENSE
ptvertmenu-0.2.2.data/data/share/doc/python-ptvertmenu/README.md
ptvertmenu-0.2.2.data/scripts/ptvertmenu-man
ptvertmenu-0.2.2.dist-info/LICENSE
ptvertmenu-0.2.2.dist-info/METADATA
ptvertmenu-0.2.2.dist-info/WHEEL
ptvertmenu-0.2.2.dist-info/top_level.txt
ptvertmenu-0.2.2.dist-info/RECORD
