Metadata-Version: 2.1
Name: ptvertmenu
Version: 0.2.2
Summary: Vertical menu widget for prompt-toolkit with optional fzf-inspired search
Home-page: http://github.com/lpenz/ptvertmenu
Author: "Leandro Lisboa Penz"
Author-email: "lpenz@lpenz.org"
License: MIT
Classifier: Development Status :: 1 - Planning
Classifier: Environment :: Console
Classifier: License :: OSI Approved :: MIT License
Classifier: Operating System :: POSIX :: Linux
Classifier: Programming Language :: Python :: 3
Requires-Python: >=3.9
License-File: LICENSE
Requires-Dist: prompt-toolkit >=3
Provides-Extra: test
Requires-Dist: pytest ; extra == 'test'
Requires-Dist: pytest-cov ; extra == 'test'
